dat_struct_py/__init__.py
dat_struct_py/linkedlist.py
dat_struct_py/queue.py
dat_struct_py/stack.py
dat_struct_py/blocks/__init__.py
dat_struct_py/blocks/node.py
dat_struct_py/tests/__init__.py
dat_struct_py/tests/testLinkedLists.py
dat_struct_py/tests/testQ.py
dat_struct_py/tests/testStacks.py
dat_struct_py-1.3.1.dist-info/METADATA
dat_struct_py-1.3.1.dist-info/RECORD
dat_struct_py-1.3.1.dist-info/WHEEL
dat_struct_py-1.3.1.dist-info/top_level.txt
