Metadata-Version: 2.1
Name: dat-struct-py
Version: 1.3.1
Summary: Basic Data Structures and Operations Implemented in Python
Home-page: https://github.com/rachit-ranjan16/dat_struct_py
Author: rachit-ranjan16
Author-email: rachit.ranjan93@gmail.com
License: GNU
Keywords: data structures operations
Platform: UNKNOWN
Classifier: Development Status :: 5 - Production/Stable
Classifier: Intended Audience :: Developers
Classifier: Topic :: Software Development
Classifier: License :: OSI Approved :: GNU General Public License (GPL)
Classifier: Programming Language :: Python :: 3.5
